pyproject_cli/__about__.py
pyproject_cli/__init__.py
pyproject_cli/cli.py
pyproject_cli-0.0.2.dist-info/METADATA
pyproject_cli-0.0.2.dist-info/WHEEL
pyproject_cli-0.0.2.dist-info/entry_points.txt
pyproject_cli-0.0.2.dist-info/licenses/LICENSE.txt
pyproject_cli-0.0.2.dist-info/RECORD
